setup.py
distributions88/Binomialdistribution.py
distributions88/Gaussiandistribution.py
distributions88/Generaldistribution.py
distributions88/__init__.py
distributions88.egg-info/PKG-INFO
distributions88.egg-info/SOURCES.txt
distributions88.egg-info/dependency_links.txt
distributions88.egg-info/not-zip-safe
distributions88.egg-info/top_level.txt